standard_fw_gen/__init__.py
standard_fw_gen/config_file_parser.py
standard_fw_gen/fw_gen.py
standard_fw_gen/fw_init.py
standard_fw_gen/move_and_gen.py
standard_fw_gen/standard_fw_gen.py
standard_fw_gen-0.0.4.dist-info/LICENSE
standard_fw_gen-0.0.4.dist-info/METADATA
standard_fw_gen-0.0.4.dist-info/WHEEL
standard_fw_gen-0.0.4.dist-info/entry_points.txt
standard_fw_gen-0.0.4.dist-info/top_level.txt
standard_fw_gen-0.0.4.dist-info/RECORD
