Metadata-Version: 2.1
Name: standard-fw-gen
Version: 0.0.4
Summary: Standard firmware generate tool
Home-page: https://gitee.com/JackLinXX_admin/standard_fw_gen
Author: Jack
Author-email: JackLinZero@163.com
License: UNKNOWN
Project-URL: Bug Tracker, https://gitee.com/JackLinXX_admin/standard_fw_gen/issues
Platform: UNKNOWN
Classifier: Programming Language :: Python :: 3
Classifier: License :: OSI Approved :: MIT License
Classifier: Operating System :: OS Independent
Requires-Python: >=3.6
License-File: LICENSE
